README.rst
setup.py
flask_apidoc/__init__.py
flask_apidoc/apidoc.py
flask_apidoc/commands.py
flask_apidoc/utils.py
flask_apidoc.egg-info/PKG-INFO
flask_apidoc.egg-info/SOURCES.txt
flask_apidoc.egg-info/dependency_links.txt
flask_apidoc.egg-info/requires.txt
flask_apidoc.egg-info/top_level.txt